django_jquery-3.1.0.dist-info/DESCRIPTION.rst
django_jquery-3.1.0.dist-info/METADATA
django_jquery-3.1.0.dist-info/RECORD
django_jquery-3.1.0.dist-info/WHEEL
django_jquery-3.1.0.dist-info/metadata.json
django_jquery-3.1.0.dist-info/top_level.txt
jquery/__init__.py
jquery/models.py
jquery/static/js/jquery.js
