Metadata-Version: 1.1
Name: django-jquery
Version: 3.1.0
Summary: jQuery packaged in an handy django app to speed up new applications and deployment.
Home-page: http://bitbucket.org/massimilianoravelli/django-jquery
Author: Massimiliano Ravelli
Author-email: massimiliano.ravelli@gmail.com
License: MIT
Keywords: django,jquery,staticfiles
Platform: any
Classifier: Development Status :: 5 - Production/Stable
Classifier: Environment :: Web Environment
Classifier: Framework :: Django
Classifier: Intended Audience :: Developers
Classifier: Natural Language :: English
Classifier: License :: OSI Approved :: MIT License
Classifier: Operating System :: OS Independent
Classifier: Programming Language :: Python
Classifier: Topic :: Utilities
